fds/__init__.py
fds/protobuf/__init__.py
fds/protobuf/stach/__init__.py
fds/protobuf/stach/v2/Package_pb2.py
fds/protobuf/stach/v2/RowOrganized_pb2.py
fds/protobuf/stach/v2/__init__.py
fds/protobuf/stach/v2/table/CellDefinition_pb2.py
fds/protobuf/stach/v2/table/ColumnData_pb2.py
fds/protobuf/stach/v2/table/ColumnDefinition_pb2.py
fds/protobuf/stach/v2/table/DataFormat_pb2.py
fds/protobuf/stach/v2/table/HorizontalAlignment_pb2.py
fds/protobuf/stach/v2/table/ListOfMetadata_pb2.py
fds/protobuf/stach/v2/table/MetadataCollection_pb2.py
fds/protobuf/stach/v2/table/MetadataItem_pb2.py
fds/protobuf/stach/v2/table/MetadataLocations_pb2.py
fds/protobuf/stach/v2/table/ReferenceType_pb2.py
fds/protobuf/stach/v2/table/Reference_pb2.py
fds/protobuf/stach/v2/table/RowDefinition_pb2.py
fds/protobuf/stach/v2/table/TableData_pb2.py
fds/protobuf/stach/v2/table/TableDefinition_pb2.py
fds/protobuf/stach/v2/table/Table_pb2.py
fds/protobuf/stach/v2/table/VerticalAlignment_pb2.py
fds/protobuf/stach/v2/table/__init__.py
fds.protobuf.stach.v2-1.0.5.dist-info/METADATA
fds.protobuf.stach.v2-1.0.5.dist-info/WHEEL
fds.protobuf.stach.v2-1.0.5.dist-info/top_level.txt
fds.protobuf.stach.v2-1.0.5.dist-info/RECORD
