Metadata-Version: 2.1
Name: fds.protobuf.stach.v2
Version: 1.0.5
Summary: Stach library in python
Home-page: UNKNOWN
Author: analytics-reporting
Author-email: analytics.api.support@factset.com
License: Apache License 2.0
Platform: UNKNOWN
Requires-Dist: protobuf<7.0.0,>=3.20.0
